esi_oephys2nwb-0.5.data/data/oephys2nwb/CHANGELOG.md
esi_oephys2nwb-0.5.data/data/oephys2nwb/CITATION.cff
esi_oephys2nwb-0.5.data/data/oephys2nwb/LICENSE
esi_oephys2nwb-0.5.data/data/oephys2nwb/README.md
oephys2nwb/__init__.py
oephys2nwb/__main__.py
oephys2nwb/export2nwb.py
esi_oephys2nwb-0.5.dist-info/BSD-3-Clause.txt
esi_oephys2nwb-0.5.dist-info/CC-BY-NC-SA-1.0.txt
esi_oephys2nwb-0.5.dist-info/CC0-1.0.txt
esi_oephys2nwb-0.5.dist-info/METADATA
esi_oephys2nwb-0.5.dist-info/WHEEL
esi_oephys2nwb-0.5.dist-info/top_level.txt
esi_oephys2nwb-0.5.dist-info/RECORD
