Metadata-Version: 2.1
Name: esi-oephys2nwb
Version: 0.5
Summary: Export binary Open Ephys data to NWB 2.x
Home-page: https://github.com/esi-neuroscience/oephys2nwb
Author: Ernst Strüngmann Institute (ESI) for Neuroscience in Cooperation with Max Planck Society
Author-email: it@esi-frankfurt.de
License: BSD-3
Project-URL: Bug Tracker, https://github.com/esi-neuroscience/oephys2nwb/issues
Project-URL: Documentation, https://esi-oephys2nwb.readthedocs.io/en/latest/
Project-URL: Source Code, https://github.com/esi-neuroscience/oephys2nwb
Classifier: Development Status :: 4 - Beta
Classifier: Environment :: Console
Classifier: Intended Audience :: Science/Research
Classifier: License :: OSI Approved :: MIT License
Classifier: Operating System :: OS Independent
Classifier: Programming Language :: Python
Classifier: Programming Language :: Python :: 3.7
Classifier: Programming Language :: Python :: 3.8
Classifier: Programming Language :: Python :: Implementation :: CPython
Requires-Python: >=3.7
License-File: LICENSES/BSD-3-Clause.txt
License-File: LICENSES/CC-BY-NC-SA-1.0.txt
License-File: LICENSES/CC0-1.0.txt
Requires-Dist: ndx-events
Requires-Dist: open-ephys-python-tools
Requires-Dist: pydantic
Requires-Dist: pynwb
Provides-Extra: dev
Requires-Dist: ipdb ; extra == 'dev'
Requires-Dist: ipython ; extra == 'dev'
Requires-Dist: numpydoc ; extra == 'dev'
Requires-Dist: sphinx-automodapi ; extra == 'dev'
Requires-Dist: sphinx-bootstrap-theme ; extra == 'dev'
